coredotdata/__init__.py
coredotdata/cli.py
coredotdata/coredotdata.py
coredotdata/download.py
coredotdata-0.4.0.dist-info/AUTHORS.md
coredotdata-0.4.0.dist-info/LICENSE
coredotdata-0.4.0.dist-info/METADATA
coredotdata-0.4.0.dist-info/WHEEL
coredotdata-0.4.0.dist-info/entry_points.txt
coredotdata-0.4.0.dist-info/top_level.txt
coredotdata-0.4.0.dist-info/RECORD
