Metadata-Version: 2.1
Name: coredotdata
Version: 0.4.0
Summary: Core.Today Dataset Management Library
Home-page: https://github.com/CoreDotToday/coredotdata
Author: Core.Today
Author-email: engine@core.today
License: Apache Software License 2.0
Keywords: coredotdata
Platform: UNKNOWN
Classifier: Development Status :: 2 - Pre-Alpha
Classifier: Intended Audience :: Developers
Classifier: License :: OSI Approved :: Apache Software License
Classifier: Natural Language :: English
Classifier: Programming Language :: Python :: 3
Classifier: Programming Language :: Python :: 3.6
Classifier: Programming Language :: Python :: 3.7
Classifier: Programming Language :: Python :: 3.8
Requires-Python: >=3.6
License-File: LICENSE
License-File: AUTHORS.md
Requires-Dist: Click (>=7.0)
Requires-Dist: requests
Requires-Dist: tqdm
